{
    "key": "613111",
    "display_name": "613111大一高工",
    "description": "大一即杀入决赛",
    "logo": "613111/logo.png",
    "table": {
        "games_played": 3,
        "wins": 2,
        "draws": 0,
        "loses": 1,
        "goals_for": 5,
        "goals_against": 1,
        "points": 6
    },
    "players": {
        "starting": [
            {
                "number": 1,
                "name": "王鸣轩",
                "img": "placeholder-player.jpg",
                "position": "门将",
                "locator": "GK",
                "played": 3,
                "goals": 0
            }
            ,{
                "number": 37,
                "name": "刘念泽",
                "img": "placeholder-player.jpg",
                "position": "后卫",
                "locator": "CB",
                "played": 3,
                "goals": 0
            }
            ,{
                "number": 16,
                "name": "熊宽晨",
                "img": "placeholder-player.jpg",
                "position": "后卫",
                "locator": "RB",
                "played": 3,
                "goals": 0
            }
            ,{
                "number": 55,
                "name": "狄学长",
                "img": "placeholder-player.jpg",
                "position": "后卫",
                "locator": "LB",
                "played": 3,
                "goals": 0
            }
            ,{
                "number": 4,
                "name": "潘登",
                "img": "placeholder-player.jpg",
                "position": "中场",
                "locator": "CM",
                "played": 3,
                "goals": 2
            }
            ,{
                "number": 9,
                "name": "沙奔",
                "img": "placeholder-player.jpg",
                "position": "前锋",
                "locator": "ST",
                "played": 3,
                "goals": 1
            }
            ,{
                "number": 31,
                "name": "孙聪",
                "img": "placeholder-player.jpg",
                "position": "中场",
                "locator": "RM",
                "played": 3,
                "goals": 0
            }
            ,{
                "number": 10,
                "name": "吉相冰",
                "img": "placeholder-player.jpg",
                "position": "前锋",
                "locator": "LM",
                "played": 3,
                "goals": 2
            }
        ],
        "subs": [
        ]
    }
}